pdf_craft/__init__.py
pdf_craft/common/__init__.py
pdf_craft/common/asset.py
pdf_craft/common/cv_splitter.py
pdf_craft/common/folder.py
pdf_craft/common/reader.py
pdf_craft/common/statistics.py
pdf_craft/common/surrogates.py
pdf_craft/common/xml.py
pdf_craft/config.py
pdf_craft/epub/__init__.py
pdf_craft/epub/latex_to_text.py
pdf_craft/epub/render.py
pdf_craft/epub/toc_collection.py
pdf_craft/error.py
pdf_craft/expression.py
pdf_craft/functions.py
pdf_craft/language.py
pdf_craft/markdown/__init__.py
pdf_craft/markdown/paragraph/__init__.py
pdf_craft/markdown/paragraph/parser.py
pdf_craft/markdown/paragraph/render.py
pdf_craft/markdown/paragraph/tags.py
pdf_craft/markdown/paragraph/types.py
pdf_craft/markdown/render/__init__.py
pdf_craft/markdown/render/layouts.py
pdf_craft/markdown/render/render.py
pdf_craft/metering.py
pdf_craft/pdf/__init__.py
pdf_craft/pdf/handler.py
pdf_craft/pdf/ocr.py
pdf_craft/pdf/page_extractor.py
pdf_craft/pdf/page_ref.py
pdf_craft/pdf/ref.py
pdf_craft/pdf/types.py
pdf_craft/sequence/__init__.py
pdf_craft/sequence/analyse_level.py
pdf_craft/sequence/chapter.py
pdf_craft/sequence/content.py
pdf_craft/sequence/generation.py
pdf_craft/sequence/jointer.py
pdf_craft/sequence/mark.py
pdf_craft/sequence/reader.py
pdf_craft/sequence/reading_serials.py
pdf_craft/sequence/reference.py
pdf_craft/to_path.py
pdf_craft/toc/__init__.py
pdf_craft/toc/analysing.py
pdf_craft/toc/text.py
pdf_craft/toc/toc_levels.py
pdf_craft/toc/toc_pages.py
pdf_craft/toc/types.py
pdf_craft/transform.py
pdf_craft-1.0.7.dist-info/LICENSE
pdf_craft-1.0.7.dist-info/METADATA
pdf_craft-1.0.7.dist-info/WHEEL
pdf_craft-1.0.7.dist-info/RECORD
