Metadata-Version: 2.3
Name: pdf-craft
Version: 1.0.7
Summary: PDF craft can convert PDF files into various other formats. This project will focus on processing PDF files of scanned books.
License: MIT
Keywords: pdf,epub,markdown
Author: Tao Zeyu
Author-email: i@taozeyu.com
Maintainer: Tao Zeyu
Maintainer-email: i@taozeyu.com
Requires-Python: >=3.10,<3.14
Classifier: Development Status :: 4 - Beta
Classifier: Intended Audience :: Developers
Classifier: License :: OSI Approved :: MIT License
Classifier: Programming Language :: Python :: 3
Classifier: Programming Language :: Python :: 3.10
Classifier: Programming Language :: Python :: 3.11
Classifier: Programming Language :: Python :: 3.12
Classifier: Programming Language :: Python :: 3.13
Classifier: Topic :: Software Development :: Libraries :: Python Modules
Classifier: Topic :: Text Processing
Requires-Dist: doc-page-extractor (==1.0.12)
Requires-Dist: epub-generator (==0.1.6)
Requires-Dist: pdf2image (>=1.17.0,<2.0.0)
Requires-Dist: pyahocorasick (>=2.2.0,<3.0.0)
Requires-Dist: pylatexenc (>=2.10,<3.0)
Requires-Dist: pypdf (>=6.4.1,<7.0.0)
Project-URL: Homepage, https://hub.oomol.com/package/pdf-craft
Project-URL: Repository, https://github.com/oomol-lab/pdf-craft
